newsatlas/__init__.py
newsatlas/core.py
newsatlas/crawler.py
newsatlas/detail_parser.py
newsatlas/models.py
newsatlas/list_parser/__init__.py
newsatlas/list_parser/extractor.py
newsatlas/list_parser/matchers/__init__.py
newsatlas/list_parser/matchers/pattern.py
newsatlas/list_parser/matchers/similarity.py
newsatlas/list_parser/utils/__init__.py
newsatlas/list_parser/utils/context.py
newsatlas/list_parser/utils/diffusion.py
newsatlas/list_parser/utils/encoding.py
newsatlas/list_parser/utils/url.py
newsatlas/list_parser/utils/url_page_type.py
newsatlas-0.1.0.dist-info/METADATA
newsatlas-0.1.0.dist-info/WHEEL
newsatlas-0.1.0.dist-info/licenses/LICENSE
newsatlas-0.1.0.dist-info/RECORD
