Metadata-Version: 2.4
Name: NewsAtlas
Version: 0.1.0
Summary: A smart news list and article content extraction library
Project-URL: Homepage, https://github.com/vibex-m/NewsAtlas
Project-URL: Documentation, https://github.com/vibex-m/NewsAtlas#readme
Project-URL: Repository, https://github.com/vibex-m/NewsAtlas
Project-URL: Issues, https://github.com/vibex-m/NewsAtlas/issues
Author-email: vibex-m <jmlnk.vibes@gmail.com>
License: Apache-2.0
License-File: LICENSE
Keywords: crawler,extraction,html-parser,news,news-aggregation,scraper,web-scraping
Classifier: Development Status :: 4 - Beta
Classifier: Intended Audience :: Developers
Classifier: License :: OSI Approved :: Apache Software License
Classifier: Operating System :: OS Independent
Classifier: Programming Language :: Python :: 3
Classifier: Programming Language :: Python :: 3.10
Classifier: Programming Language :: Python :: 3.11
Classifier: Programming Language :: Python :: 3.12
Classifier: Topic :: Internet :: WWW/HTTP :: Indexing/Search
Classifier: Topic :: Text Processing :: Markup :: HTML
Requires-Python: >=3.10
Requires-Dist: build>=1.4.0
Requires-Dist: charset-normalizer>=3.0.0
Requires-Dist: cssselect>=1.2.0
Requires-Dist: dateparser>=1.1.0
Requires-Dist: lxml>=4.9.0
Requires-Dist: requests>=2.28.0
Requires-Dist: trafilatura>=1.6.0
Provides-Extra: dev
Requires-Dist: mypy>=1.0; extra == 'dev'
Requires-Dist: pytest-cov>=4.0; extra == 'dev'
Requires-Dist: pytest>=7.0; extra == 'dev'
Requires-Dist: ruff>=0.1.0; extra == 'dev'
